azure/cosmosdb/__init__.py
azure_cosmosdb_nspkg-2.0.1.dist-info/DESCRIPTION.rst
azure_cosmosdb_nspkg-2.0.1.dist-info/METADATA
azure_cosmosdb_nspkg-2.0.1.dist-info/RECORD
azure_cosmosdb_nspkg-2.0.1.dist-info/WHEEL
azure_cosmosdb_nspkg-2.0.1.dist-info/metadata.json
azure_cosmosdb_nspkg-2.0.1.dist-info/top_level.txt
