Metadata-Version: 2.0
Name: azure-cosmosdb-nspkg
Version: 2.0.1
Summary: Microsoft Azure CosmosDB Namespace Package [Internal]
Home-page: https://github.com/Azure/azure-cosmosdb-python
Author: Microsoft Corporation
Author-email: ascl@microsoft.com
License: Apache License 2.0
Platform: UNKNOWN
Classifier: Development Status :: 5 - Production/Stable
Classifier: Programming Language :: Python
Classifier: Programming Language :: Python :: 2
Classifier: Programming Language :: Python :: 2.7
Classifier: Programming Language :: Python :: 3
Classifier: Programming Language :: Python :: 3.3
Classifier: Programming Language :: Python :: 3.4
Classifier: Programming Language :: Python :: 3.5
Classifier: Programming Language :: Python :: 3.6
Classifier: License :: OSI Approved :: Apache Software License
Requires-Dist: azure-nspkg (>=2.0.0)
